response_mocker/__init__.py
response_mocker/response_mocker.py
response_mocker-1.0.8.dist-info/DESCRIPTION.rst
response_mocker-1.0.8.dist-info/METADATA
response_mocker-1.0.8.dist-info/RECORD
response_mocker-1.0.8.dist-info/WHEEL
response_mocker-1.0.8.dist-info/metadata.json
response_mocker-1.0.8.dist-info/pbr.json
response_mocker-1.0.8.dist-info/top_level.txt
