Metadata-Version: 2.0
Name: response-mocker
Version: 1.0.8
Summary: A simple mocking library for Requests
Home-page: https://github.com/menge101/response_mocker
Author: Nathan Menge
Author-email: nathan.menge@gmail.com
License: MIT
Platform: UNKNOWN
Requires-Dist: future
